pleque/__init__.py
pleque/core/__init__.py
pleque/core/cocos.py
pleque/core/coordinates.py
pleque/core/equilibrium.py
pleque/core/fluxfunctions.py
pleque/core/fluxsurface.py
pleque/core/surfacefunctions.py
pleque/core/interpolators/__init__.py
pleque/core/math/__init__.py
pleque/io/__init__.py
pleque/io/_fileutils.py
pleque/io/_geqdsk.py
pleque/io/_magics.py
pleque/io/_readgeqdsk.py
pleque/io/_test_gfile_loader.py
pleque/io/compass.py
pleque/io/geqdsk.py
pleque/io/metis.py
pleque/io/omas.py
pleque/io/readers.py
pleque/io/tools.py
pleque/io/jet/__init__.py
pleque/io/jet/reader_jet.py
pleque/resources/14068@1130_2kA_modified_triang.gfile
pleque/resources/DoubleNull_eqdsk
pleque/resources/__init__.py
pleque/resources/baseline_eqdsk
pleque/resources/g13127.1050
pleque/resources/g15349.1120
pleque/resources/limiter_v3_1_iba.dat
pleque/resources/limiter_v3_1_iba_v2.dat
pleque/resources/metis.mat
pleque/resources/scenario_1_baseline_upward_eqdsk
pleque/resources/shot8078_jorek_data.nc
pleque/resources/test00.gfile
pleque/resources/test00.nc
pleque/spatran/__init__.py
pleque/spatran/affine.py
pleque/spatran/reference_frames.py
pleque/tests/__init__.py
pleque/tests/utils.py
pleque/utils/__init__.py
pleque/utils/decorators.py
pleque/utils/equi_tools.py
pleque/utils/field_line_tracers.py
pleque/utils/flux_expansions.py
pleque/utils/plotting.py
pleque/utils/surfaces.py
pleque/utils/tools.py
tests/__init__.py
tests/compu_test.py
tests/conftest.py
tests/surfaces_test.py
tests/test_2Dinterpolation.py
tests/test_affine.py
tests/test_cdb.py
tests/test_cocos.py
tests/test_coordinates.py
tests/test_equilibria.py
tests/test_fluxexpansion.py
tests/test_functions.py
tests/test_gfile.py
tests/test_io.py
tests/test_metis.py
tests/test_omas.py
tests/test_surface_param.py
pleque-0.0.7.dist-info/LICENSE
pleque-0.0.7.dist-info/METADATA
pleque-0.0.7.dist-info/WHEEL
pleque-0.0.7.dist-info/top_level.txt
pleque-0.0.7.dist-info/RECORD
