Metadata-Version: 2.1
Name: pleque
Version: 0.0.7
Summary: Python module for an easy work with a tokamak plasma equilibrium.
Home-page: https://pleque.readthedocs.io
Download-URL: https://github.com/kripnerl/pleque
Author: Lukas Kripner
Author-email: kripner@ipp.cas.cz
License: MIT
License-File: LICENSE
Requires-Dist: numpy
Requires-Dist: scipy
Requires-Dist: shapely (<2.0.0)
Requires-Dist: xarray
Requires-Dist: scikit-image (>=0.14.2)
Requires-Dist: h5py
Requires-Dist: omas
